sem_meta/OCR_NOISE_DB.py
sem_meta/SEMKEYS.py
sem_meta/__init__.py
sem_meta/_version.py
sem_meta/convert_Module.py
sem_meta/metadata_Module.py
sem_meta/ocr_Module.py
sem_meta/model/ell.user-patterns
sem_meta/model/ell.user-words
sem_meta/ref_scale/scale_reference.jpg
sem_meta-0.1.1.dist-info/licenses/LICENSE
sem_meta-0.1.1.dist-info/METADATA
sem_meta-0.1.1.dist-info/WHEEL
sem_meta-0.1.1.dist-info/top_level.txt
sem_meta-0.1.1.dist-info/RECORD
