Metadata-Version: 2.4
Name: sem-meta
Version: 0.1.1
Summary: Unified interface for SEM image processing: metadata extraction, OCR-based pixel size estimation, and unit conversion
Home-page: https://github.com/asaleh33/sem-meta
Author: Ahmed Khalil, Tommaso Rodani
Author-email: Ahmed Khalil <salehastro@gmail.com>, Tommaso Rodani <tommaso.rodani.phd@gmail.com>
Maintainer-email: Ahmed Khalil <salehastro@gmail.com>, Tommaso Rodani <tommaso.rodani.phd@gmail.com>
License: MIT
Project-URL: Homepage, https://github.com/asaleh33/sem-meta
Project-URL: Repository, https://github.com/asaleh33/sem-meta
Project-URL: Documentation, https://github.com/asaleh33/sem-meta#readme
Project-URL: Bug Tracker, https://github.com/asaleh33/sem-meta/issues
Keywords: SEM,microscopy,image processing,metadata extraction,OCR,pixel size,scientific imaging,electron microscopy
Classifier: Development Status :: 4 - Beta
Classifier: Intended Audience :: Science/Research
Classifier: Intended Audience :: Developers
Classifier: License :: OSI Approved :: MIT License
Classifier: Operating System :: OS Independent
Classifier: Programming Language :: Python :: 3
Classifier: Programming Language :: Python :: 3.7
Classifier: Programming Language :: Python :: 3.8
Classifier: Programming Language :: Python :: 3.9
Classifier: Programming Language :: Python :: 3.10
Classifier: Programming Language :: Python :: 3.11
Classifier: Programming Language :: Python :: 3.12
Classifier: Topic :: Scientific/Engineering
Classifier: Topic :: Scientific/Engineering :: Image Processing
Classifier: Topic :: Software Development :: Libraries :: Python Modules
Requires-Python: >=3.7
License-File: LICENSE
Requires-Dist: numpy>=1.19.0
Requires-Dist: Pillow>=8.0.0
Requires-Dist: PyMySQL>=1.0.0
Requires-Dist: termcolor>=1.1.0
Requires-Dist: matplotlib>=3.3.0
Requires-Dist: opencv-python>=4.5.0
Requires-Dist: pytesseract>=0.3.8
Provides-Extra: dev
Requires-Dist: pytest>=6.0; extra == "dev"
Requires-Dist: pytest-cov>=2.0; extra == "dev"
Requires-Dist: black>=21.0; extra == "dev"
Requires-Dist: flake8>=3.8; extra == "dev"
Requires-Dist: mypy>=0.800; extra == "dev"
Provides-Extra: docs
Requires-Dist: sphinx>=4.0; extra == "docs"
Requires-Dist: sphinx-rtd-theme>=1.0; extra == "docs"
Dynamic: license-file
